README.rst
bottleCBV.py
setup.cfg
setup.py
BottleCBV.egg-info/PKG-INFO
BottleCBV.egg-info/SOURCES.txt
BottleCBV.egg-info/dependency_links.txt
BottleCBV.egg-info/not-zip-safe
BottleCBV.egg-info/requires.txt
BottleCBV.egg-info/top_level.txt