Metadata-Version: 1.1
Name: BottleCBV
Version: 0.2
Summary: Class based views for Bottle apps
Home-page: https://github.com/techchunks/bottleCBV
Author: Technology Chunks
Author-email: aedil12155@gmail.com
License: BSD
Keywords: bottle,bottlepy,class-based-view
Platform: any
Classifier: Programming Language :: Python
Classifier: Development Status :: 4 - Beta
Classifier: Environment :: Other Environment
Classifier: Intended Audience :: Developers
Classifier: License :: OSI Approved :: GNU Library or Lesser General Public License (LGPL)
Classifier: Operating System :: OS Independent
Classifier: Topic :: Software Development :: Libraries :: Python Modules
Classifier: Framework :: Bottle
